bcsdk/__init__.py
bcsdk/bcsdk.py
bcsdk/logginghandler.py
bcsdk/examples/__init__.py
bcsdk/examples/mathoperations.py
bcsdk/impl/impl.py
bcsdk/impl/sio.py
braincube_model_sdk-0.1.4.dist-info/METADATA
braincube_model_sdk-0.1.4.dist-info/WHEEL
braincube_model_sdk-0.1.4.dist-info/entry_points.txt
braincube_model_sdk-0.1.4.dist-info/top_level.txt
braincube_model_sdk-0.1.4.dist-info/RECORD
