Metadata-Version: 2.1
Name: braincube-model-sdk
Version: 0.1.4
Summary: The Braincube Python Edge SDK
Home-page: https://mybraincube.com
Author: Braincube
Author-email: contact@braincube.com
License: MIT
Platform: UNKNOWN
Requires-Python: >3.6
Requires-Dist: Flask-SocketIO (<5,>=4.3.2)
Requires-Dist: requests (==2.24.0)
